purpose_transcribe/__init__.py
purpose_transcribe/main.py
purpose_transcribe/transcription.py
purpose_transcribe/utils.py
purpose_transcribe-0.2.1.dist-info/LICENSE
purpose_transcribe-0.2.1.dist-info/METADATA
purpose_transcribe-0.2.1.dist-info/WHEEL
purpose_transcribe-0.2.1.dist-info/entry_points.txt
purpose_transcribe-0.2.1.dist-info/top_level.txt
purpose_transcribe-0.2.1.dist-info/RECORD
