Metadata-Version: 2.1
Name: purpose_transcribe
Version: 0.2.1
Summary: A CLI tool for transcribing audio files
Author: Mark Okello
Author-email: markokello55@gmail.com
License: MIT
Classifier: Development Status :: 3 - Alpha
Classifier: Intended Audience :: Developers
Classifier: Topic :: Software Development :: Build Tools
Classifier: License :: OSI Approved :: MIT License
Classifier: Programming Language :: Python :: 3.9
Classifier: Programming Language :: Python :: 3.10
Classifier: Programming Language :: Python :: 3.11
Requires-Python: >=3.9
License-File: LICENSE
Requires-Dist: click
Requires-Dist: openai-whisper
